<?xml version="1.0" encoding="UTF-8" standalone="no"?>
<Gesture Milliseconds="833" Name="V2" NumPts="55" Number="2">
    <Point T="1678" X="318.0" Y="113.0"/>
    <Point T="1678" X="318.0" Y="113.0"/>
    <Point T="1678" X="319.0" Y="113.0"/>
    <Point T="1678" X="320.0" Y="116.0"/>
    <Point T="1678" X="323.0" Y="125.0"/>
    <Point T="1678" X="328.0" Y="134.0"/>
    <Point T="1678" X="331.0" Y="143.0"/>
    <Point T="1678" X="336.0" Y="152.0"/>
    <Point T="1678" X="341.0" Y="166.0"/>
    <Point T="1678" X="345.0" Y="177.0"/>
    <Point T="1678" X="350.0" Y="186.0"/>
    <Point T="1678" X="350.0" Y="188.0"/>
    <Point T="1678" X="355.0" Y="199.0"/>
    <Point T="1678" X="357.0" Y="205.0"/>
    <Point T="1678" X="362.0" Y="217.0"/>
    <Point T="1678" X="363.0" Y="221.0"/>
    <Point T="1678" X="366.0" Y="230.0"/>
    <Point T="1678" X="370.0" Y="239.0"/>
    <Point T="1678" X="373.0" Y="246.0"/>
    <Point T="1678" X="375.0" Y="252.0"/>
    <Point T="1678" X="376.0" Y="255.0"/>
    <Point T="1678" X="378.0" Y="259.0"/>
    <Point T="1678" X="380.0" Y="262.0"/>
    <Point T="1678" X="380.0" Y="263.0"/>
    <Point T="1678" X="381.0" Y="266.0"/>
    <Point T="1678" X="381.0" Y="266.0"/>
    <Point T="1678" X="381.0" Y="267.0"/>
    <Point T="1678" X="382.0" Y="266.0"/>
    <Point T="1678" X="382.0" Y="266.0"/>
    <Point T="1678" X="385.0" Y="260.0"/>
    <Point T="1678" X="385.0" Y="259.0"/>
    <Point T="1678" X="391.0" Y="251.0"/>
    <Point T="1678" X="396.0" Y="242.0"/>
    <Point T="1678" X="404.0" Y="232.0"/>
    <Point T="1678" X="408.0" Y="224.0"/>
    <Point T="1678" X="411.0" Y="219.0"/>
    <Point T="1678" X="418.0" Y="209.0"/>
    <Point T="1678" X="424.0" Y="200.0"/>
    <Point T="1678" X="429.0" Y="189.0"/>
    <Point T="1678" X="435.0" Y="178.0"/>
    <Point T="1678" X="440.0" Y="171.0"/>
    <Point T="1678" X="446.0" Y="160.0"/>
    <Point T="1678" X="450.0" Y="148.0"/>
    <Point T="1678" X="453.0" Y="142.0"/>
    <Point T="1678" X="458.0" Y="132.0"/>
    <Point T="1678" X="460.0" Y="127.0"/>
    <Point T="1678" X="462.0" Y="122.0"/>
    <Point T="1678" X="465.0" Y="113.0"/>
    <Point T="1678" X="467.0" Y="108.0"/>
    <Point T="1678" X="468.0" Y="104.0"/>
    <Point T="1678" X="468.0" Y="103.0"/>
    <Point T="1678" X="469.0" Y="102.0"/>
    <Point T="1678" X="469.0" Y="102.0"/>
    <Point T="1678" X="469.0" Y="101.0"/>
    <Point T="1678" X="469.0" Y="101.0"/>
</Gesture>
